iAI/__init__.py
iAI-0.0.1.dist-info/LICENSE
iAI-0.0.1.dist-info/METADATA
iAI-0.0.1.dist-info/WHEEL
iAI-0.0.1.dist-info/top_level.txt
iAI-0.0.1.dist-info/RECORD
