Metadata-Version: 2.1
Name: iAI
Version: 0.0.1
Summary: innovata-sambong-AI
Home-page: https://github.com/innovata/iAI
Author: innovata sambong
Author-email: iinnovata@gmail.com
License: UNKNOWN
Platform: UNKNOWN
Classifier: Programming Language :: Python :: 3
Classifier: License :: OSI Approved :: MIT License
Classifier: Operating System :: OS Independent
